test
yandex_checkout
