Metadata-Version: 2.1
Name: yandex-checkout
Version: 1.6.5
Summary: Yandex Checkout SDK Python Library
Home-page: https://github.com/yandex-money/yandex-checkout-sdk-python
Author: Yandex.Money
License: MIT
Platform: UNKNOWN
Classifier: License :: OSI Approved :: MIT License
Classifier: Programming Language :: Python :: 2.7
Classifier: Programming Language :: Python :: 3.4
Classifier: Programming Language :: Python :: 3.5
Classifier: Programming Language :: Python :: 3.6
Classifier: Programming Language :: Python :: 3.7
Classifier: Programming Language :: Python :: 3.8
